{
  "version": "5.0.0",
  "flags": {},
  "shapes": [
    {
      "label": "anchor_square",
      "points": [
        [
          244.5731201171875,
          559.3397827148438
        ],
        [
          261.1511535644531,
          527.9241333007812
        ],
        [
          502.1431579589844,
          521.8328857421875
        ],
        [
          506.7391357421875,
          759.1404418945312
        ],
        [
          472.8862609863281,
          766.2173461914062
        ],
        [
          249.31861877441406,
          762.7779541015625
        ]
      ],
      "group_id": null,
      "shape_type": "polygon",
      "flags": {}
    },
    {
      "label": "score_1_triangle",
      "points": [
        [
          493.69183349609375,
          25.714418411254883
        ],
        [
          494.3641662597656,
          269.49853515625
        ],
        [
          252.50611877441406,
          30.8666934967041
        ],
        [
          495.6575927734375,
          21.62470245361328
        ],
        [
          494.9615478515625,
          49.803497314453125
        ]
      ],
      "group_id": null,
      "shape_type": "polygon",
      "flags": {}
    },
    {
      "label": "score_1_triangle",
      "points": [
        [
          185.5340576171875,
          413.82421875
        ],
        [
          19.697711944580078,
          563.892578125
        ],
        [
          25.443899154663086,
          228.23898315429688
        ],
        [
          182.1233673095703,
          384.9873352050781
        ],
        [
          191.45477294921875,
          407.63653564453125
        ]
      ],
      "group_id": null,
      "shape_type": "polygon",
      "flags": {}
    }
  ],
  "imagePath": "mirror_blue_1_card_00.png",
  "imageData": null,
  "imageHeight": 801,
  "imageWidth": 536
}